README.rst
setup.py
safe_redis_lock/__init__.py
safe_redis_lock/redis_lock.py
safe_redis_lock.egg-info/PKG-INFO
safe_redis_lock.egg-info/SOURCES.txt
safe_redis_lock.egg-info/dependency_links.txt
safe_redis_lock.egg-info/requires.txt
safe_redis_lock.egg-info/top_level.txt