Metadata-Version: 1.0
Name: safe-redis-lock
Version: 0.1
Summary: a safe redis lock in Single node Redis
Home-page: https://gitee.com
Author: liuyancong
Author-email: lyc456789@163.com
License: MIT
Platform: UNKNOWN
